odoo/addons/l10n_es_ticketbai/README.rst
odoo/addons/l10n_es_ticketbai/__init__.py
odoo/addons/l10n_es_ticketbai/__manifest__.py
odoo/addons/l10n_es_ticketbai/hooks.py
odoo/addons/l10n_es_ticketbai/data/account_fiscal_position_template.xml
odoo/addons/l10n_es_ticketbai/data/tax_map_data.xml
odoo/addons/l10n_es_ticketbai/data/vat_exemption_key_data.xml
odoo/addons/l10n_es_ticketbai/data/vat_regime_key_data.xml
odoo/addons/l10n_es_ticketbai/i18n/ca.po
odoo/addons/l10n_es_ticketbai/i18n/es.po
odoo/addons/l10n_es_ticketbai/i18n/eu.po
odoo/addons/l10n_es_ticketbai/i18n/l10n_es_ticketbai.pot
odoo/addons/l10n_es_ticketbai/migrations/14.0.1.0.1/post-migration.py
odoo/addons/l10n_es_ticketbai/migrations/14.0.1.2.0/post-migrate.py
odoo/addons/l10n_es_ticketbai/migrations/14.0.2.7.6/post-migrate.py
odoo/addons/l10n_es_ticketbai/migrations/14.0.2.8.4/post-migration.py
odoo/addons/l10n_es_ticketbai/migrations/14.0.2.8.4/pre-migration.py
odoo/addons/l10n_es_ticketbai/migrations/14.0.2.8.5/post-migration.py
odoo/addons/l10n_es_ticketbai/models/__init__.py
odoo/addons/l10n_es_ticketbai/models/account_fiscal_position.py
odoo/addons/l10n_es_ticketbai/models/account_journal.py
odoo/addons/l10n_es_ticketbai/models/account_move.py
odoo/addons/l10n_es_ticketbai/models/account_resequence.py
odoo/addons/l10n_es_ticketbai/models/account_tax.py
odoo/addons/l10n_es_ticketbai/models/aeat_certificate.py
odoo/addons/l10n_es_ticketbai/models/chart_template.py
odoo/addons/l10n_es_ticketbai/models/ir_sequence.py
odoo/addons/l10n_es_ticketbai/models/res_company.py
odoo/addons/l10n_es_ticketbai/models/ticketbai_invoice.py
odoo/addons/l10n_es_ticketbai/models/ticketbai_tax_map.py
odoo/addons/l10n_es_ticketbai/models/ticketbai_vat_exemption_key.py
odoo/addons/l10n_es_ticketbai/models/ticketbai_vat_regime_key.py
odoo/addons/l10n_es_ticketbai/readme/CONFIGURE.rst
odoo/addons/l10n_es_ticketbai/readme/CONTRIBUTORS.rst
odoo/addons/l10n_es_ticketbai/readme/DESCRIPTION.rst
odoo14_addon_l10n_es_ticketbai-14.0.2.9.3.dist-info/METADATA
odoo14_addon_l10n_es_ticketbai-14.0.2.9.3.dist-info/WHEEL
odoo14_addon_l10n_es_ticketbai-14.0.2.9.3.dist-info/top_level.txt
odoo14_addon_l10n_es_ticketbai-14.0.2.9.3.dist-info/RECORD
