Metadata-Version: 2.1
Name: odoo14-addon-l10n-es-ticketbai
Version: 14.0.2.9.3
Summary: Declaración de todas las operaciones de venta realizadas por las personas y entidades que desarrollan actividades económicas
Home-page: https://github.com/OCA/l10n-spain
Author: Binovo, Odoo Community Association (OCA)
Author-email: support@odoo-community.org
License: AGPL-3
Platform: UNKNOWN
Classifier: Programming Language :: Python
Classifier: Framework :: Odoo
Classifier: Framework :: Odoo :: 14.0
Classifier: License :: OSI Approved :: GNU Affero General Public License v3
Classifier: Development Status :: 4 - Beta
Requires-Python: >=3.6
Requires-Dist: cryptography (<39)
Requires-Dist: odoo14-addon-l10n-es-aeat
Requires-Dist: odoo14-addon-l10n-es-ticketbai-api
Requires-Dist: odoo (<14.1dev,>=14.0a)
